mopet/__init__.py
mopet/exceptions.py
mopet/mopet.py
mopet-0.1.7.dist-info/LICENSE
mopet-0.1.7.dist-info/METADATA
mopet-0.1.7.dist-info/WHEEL
mopet-0.1.7.dist-info/top_level.txt
mopet-0.1.7.dist-info/RECORD
