Metadata-Version: 2.1
Name: mopet
Version: 0.1.7
Summary: The mildly ominous parameter exploration toolkit
Home-page: https://github.com/caglorithm/mopet
Author: Caglar Cakan
Author-email: cakan@ni.tu-berlin.de
License: MIT
Platform: UNKNOWN
Classifier: Programming Language :: Python :: 3
Classifier: License :: OSI Approved :: MIT License
Classifier: Operating System :: OS Independent
Requires-Python: >=3.6
Requires-Dist: ray
Requires-Dist: numpy (>=1.16)
Requires-Dist: tables
Requires-Dist: pandas
Requires-Dist: tqdm
Requires-Dist: aiohttp
Requires-Dist: psutil
Requires-Dist: setproctitle
Requires-Dist: grpcio
